spi_adxl362_controller/spi_adxl362_controller/spi_adxl362_controller.srcs/sources_1/new/spi_adxl362_controller.sv
`timescale 1ns / 1ps
module spi_adxl362_controller(
    input i_clk,
    input i_rst,
    
    output reg o_csn,
    output reg o_sclk,
    output reg o_mosi,
    input      i_miso,

    input i_ready,
    input [7:0] i_inst,
    input i_sel_rw,
    input [7:0] i_reg_addr,
    input [7:0] i_dout,
    output reg [7:0] o_din,
    output reg       o_din_valid
    );

    // o_sclk gen, 5Mhz output

    reg r_sclk_en;
    reg r_sclk_d;
    reg [7:0] r_sclk_count;
    wire w_sclk_posedge;
    wire w_sclk_negedge;  

    always @(posedge i_clk) begin
        if (i_rst || ~r_sclk_en) begin
            o_sclk <= 1'b0;
            r_sclk_count <= 8'd0;
        end
        else if (r_sclk_en && (r_sclk_count < 8'd10)) begin
            r_sclk_count <= r_sclk_count + 8'd1;
        end else begin
            o_sclk <= ~o_sclk;
            r_sclk_count <= 8'd0;
        end
    end

    // determine edge of o_sclk

    always @(posedge i_clk) begin
        if (i_rst) begin
            r_sclk_d <= o_sclk;
        end else r_sclk_d <= o_sclk;
    end

    assign w_sclk_posedge = ({r_sclk_d, o_sclk} == 2'b01) ? 1'b1 : 1'b0;
    assign w_sclk_negedge = ({r_sclk_d, o_sclk} == 2'b10) ? 1'b1 : 1'b0;

    // determine edge of ready

    reg r_ready_d;
    wire w_ready_posedge;
    always @(posedge i_clk) begin
        r_ready_d <= i_ready;
    end
    assign w_ready_posedge = ({r_ready_d, i_ready} == 2'b01) ? 1'b1 : 1'b0;

    // state machine 

    reg [2:0] r_state;
    reg [2:0] r_next_state;
    
    parameter IDLE = 3'd0;
    parameter START = 3'd1;
    parameter INST_OUT = 3'd2;
    parameter ADDR_OUT = 3'd3;
    parameter WRITE_DATA = 3'd4;
    parameter READ_DATA = 3'd5;
    parameter ENDING = 3'd6;

    reg [7:0] r_mosi_buf;
    reg [6:0] r_miso_buf;
    reg [2:0] r_bitcount;

    always @(posedge i_clk) begin
        if (i_rst) begin
            r_state <= IDLE;
        end else begin
            r_state <= r_next_state;
        end
    end

    always @(posedge i_clk) begin
        case (r_state)
            IDLE:begin
                r_next_state <= START;
                o_mosi <= 1'b0;
                o_csn <= 1'b1;
                r_sclk_en <= 1'b0;
                r_mosi_buf <= i_inst;
                r_bitcount <= 3'd0;
                o_din <= 8'd0;
                o_din_valid <= 1'b0;
            end 
            START: begin
                if (w_ready_posedge) begin
                    o_csn <= 1'b0;
                    r_sclk_en <= 1'b1;
                    r_mosi_buf <= {i_inst[6:0], 1'b0};
                    o_mosi <= i_inst[7];
                    r_next_state <= INST_OUT;
                end
            end
            INST_OUT: begin
                if (w_sclk_negedge &&  (r_bitcount < 3'd7)) begin
                    {o_mosi, r_mosi_buf} <= {r_mosi_buf, 1'b0};
                    r_bitcount <= r_bitcount + 3'd1;
                end
                else if (w_sclk_negedge) begin
                    {o_mosi, r_mosi_buf} <= {i_reg_addr, 1'b0};
                    r_bitcount <= 3'd0;
                    r_next_state <= ADDR_OUT;
                end
            end
            ADDR_OUT: begin
                if (w_sclk_negedge && (r_bitcount < 3'd7)) begin
                    {o_mosi, r_mosi_buf} <= {r_mosi_buf, 1'b0};
                    r_bitcount <= r_bitcount + 3'd1;
                end
                else if (w_sclk_negedge) begin
                    {o_mosi, r_mosi_buf} <= {i_dout, 1'b0};
                    r_bitcount <= 3'd0;
                    if (i_sel_rw) begin
                        r_next_state <= READ_DATA;
                    end else begin
                        r_next_state <= WRITE_DATA;
                    end
                end
            end
            WRITE_DATA:
            begin
                if (w_sclk_negedge && (r_bitcount < 3'd7)) begin
                    {o_mosi, r_mosi_buf} <= {r_mosi_buf, 1'b0};
                    r_bitcount <= r_bitcount + 4'd1;
                end
                else if (w_sclk_negedge) begin
                    {o_mosi, r_mosi_buf} <= 9'h0;
                    r_bitcount <= 3'd0;
                    r_next_state <= ENDING;
                end
            end
            READ_DATA:
            begin
                if (w_sclk_posedge && (r_bitcount < 4'd7)) begin
                    r_miso_buf <= {r_miso_buf[5:0], i_miso};
                    r_bitcount <= r_bitcount + 3'd1;
                end
                else if (w_sclk_posedge) begin
                    r_bitcount <= 3'd0;
                    o_din <= {r_miso_buf, i_miso};
                    o_din_valid <= 1'b1;
                    r_next_state <= ENDING;
                end
                else begin
                    o_din_valid <= 1'b0;
                end
            end
            ENDING:
            begin
                if (w_sclk_negedge) begin
                    o_csn <= 1'b1;
                    r_sclk_en <= 1'b0;
                    r_next_state <= IDLE;
                end
            end
            default: r_next_state <= r_state;
        endcase
    end
endmodule

spi_adxl362_controller/spi_adxl362_controller/spi_adxl362_controller.srcs/sim_1/new/spi_adxl362_controller_tb.sv
`timescale 1ns / 1ps
module spi_adxl362_controller_tb;

  // -----------------------
  // DUT ports
  // -----------------------
  reg         i_clk;
  reg         i_rst;

  wire        o_csn;
  wire        o_sclk;
  wire        o_mosi;
  reg         i_miso;

  reg         i_ready;
  reg  [7:0]  i_inst;
  reg         i_sel_rw;     // 0: WRITE, 1: READ
  reg  [7:0]  i_reg_addr;
  reg  [7:0]  i_dout;
  wire [7:0]  o_din;
  wire        o_din_valid;

  // -----------------------
  // Instantiate DUT
  // -----------------------
  spi_adxl362_controller dut (
    .i_clk      (i_clk),
    .i_rst      (i_rst),
    .o_csn      (o_csn),
    .o_sclk     (o_sclk),
    .o_mosi     (o_mosi),
    .i_miso     (i_miso),
    .i_ready    (i_ready),
    .i_inst     (i_inst),
    .i_sel_rw   (i_sel_rw),
    .i_reg_addr (i_reg_addr),
    .i_dout     (i_dout),
    .o_din      (o_din),
    .o_din_valid(o_din_valid)
  );

  // -----------------------
  // Clock: 100 MHz
  // -----------------------
  initial i_clk = 1'b0;
  always  #5 i_clk = ~i_clk;

  // -----------------------
  // VCD (tùy ch?n)
  // -----------------------
  initial begin
    $dumpfile("spi_tx1byte.vcd");
    $dumpvars(0, spi_adxl362_controller_tb);
  end

  // -----------------------
  // Monitor s? ki?n (tùy ch?n)
  // -----------------------
  always @(negedge o_csn)  $display("[%0t] CSN FALL (frame start)", $time);
  always @(posedge o_csn)  $display("[%0t] CSN RISE  (frame end)",   $time);

  // -----------------------
  // B?t MOSI trong 1 frame ghi 24 bit (INST+ADDR+DATA)
  // -----------------------
  reg [23:0] mosi_stream;  // ch?a 24 bit ?ã thu
  integer    bit_cnt;

  // Thu bit MOSI ? c?nh xu?ng SCLK khi CSN=0 (SPI mode 0)
  always @(negedge o_sclk) begin
    if (o_csn == 1'b0) begin
      mosi_stream <= {mosi_stream[22:0], o_mosi}; // d?ch trái, thêm bit m?i vào LSB
      bit_cnt     <= bit_cnt + 1;
    end
  end

  // -----------------------
  // Reset & 1 giao d?ch WRITE (1 byte)
  // -----------------------
  initial begin
    // defaults
    i_miso     = 1'b0;
    i_ready    = 1'b0;
    i_inst     = 8'h00;
    i_sel_rw   = 1'b0;       // WRITE
    i_reg_addr = 8'h00;
    i_dout     = 8'h00;

    mosi_stream = 24'h0;
    bit_cnt     = 0;

    // reset
    i_rst = 1'b1;
    repeat (10) @(posedge i_clk);
    i_rst = 1'b0;

    // chu?n b? n?i dung giao d?ch: WRITE 0x02 vào addr 0x2D
    @(posedge i_clk);
    i_inst     <= 8'h0A;     // ADXL362 WRITE
    i_sel_rw   <= 1'b0;      // WRITE
    i_reg_addr <= 8'h2D;
    i_dout     <= 8'h02;

    // nhá i_ready ?úng 1 chu k?
    @(posedge i_clk);
    i_ready <= 1'b1;
    @(posedge i_clk);
    i_ready <= 1'b0;

    // ch? b?t ??u frame
    @(negedge o_csn);
    // reset b? ??m/buffer tr??c khi thu 24 bit
    mosi_stream = 24'h0;
    bit_cnt     = 0;

    // ch? ?? 24 c?nh xu?ng (8b INST + 8b ADDR + 8b DATA)
    wait (bit_cnt >= 24);

    // ch? k?t thúc frame (CSN lên l?i)
    @(posedge o_csn);

    // K? v?ng: MSB-first, ta ?ã thu theo th? t? MSB->LSB vào mosi_stream b?ng d?ch trái
    // nên mosi_stream ph?i b?ng {INST, ADDR, DATA}
    #1; // nh? ?? ??m b?o c?p nh?t non-blocking xong
    $display("[%0t] Collected 24 MOSI bits: 0x%06h", $time, mosi_stream);
    $display("Expected                 : 0x%06h", {i_inst, i_reg_addr, i_dout});

    if (mosi_stream === {i_inst, i_reg_addr, i_dout})
      $display("RESULT: PASS (MOSI matches INST|ADDR|DATA)");
    else
      $display("RESULT: FAIL (MOSI mismatch)");

    // k?t thúc
    #(2000);
    $display("[%0t] Test finished.", $time);
    $finish;
  end

endmodule

spi_adxl362_controller/spi_adxl362_controller/spi_adxl362_controller.sim/sim_1/behav/xsim/spi_tx1byte.vcd
$date
   Mon Oct 20 09:23:03 2025
$end
$version
  2019.2
$end
$timescale
  1ps
$end
$scope module spi_adxl362_controller_tb $end
$var reg 1 ! i_clk $end
$var reg 1 " i_rst $end
$var wire 1 # o_csn $end
$var wire 1 $ o_sclk $end
$var wire 1 % o_mosi $end
$var reg 1 & i_miso $end
$var reg 1 ' i_ready $end
$var reg 8 ( i_inst [7:0] $end
$var reg 1 ) i_sel_rw $end
$var reg 8 * i_reg_addr [7:0] $end
$var reg 8 + i_dout [7:0] $end
$var wire 8 , o_din [7:0] $end
$var wire 1 - o_din_valid $end
$var reg 24 . mosi_stream [23:0] $end
$var integer 32 / bit_cnt $end
$scope module dut $end
$var wire 1 0 i_clk $end
$var wire 1 1 i_rst $end
$var reg 1 2 o_csn $end
$var reg 1 3 o_sclk $end
$var reg 1 4 o_mosi $end
$var wire 1 5 i_miso $end
$var wire 1 6 i_ready $end
$var wire 8 7 i_inst [7:0] $end
$var wire 1 8 i_sel_rw $end
$var wire 8 9 i_reg_addr [7:0] $end
$var wire 8 : i_dout [7:0] $end
$var reg 8 ; o_din [7:0] $end
$var reg 1 < o_din_valid $end
$var reg 1 = r_sclk_en $end
$var reg 1 > r_sclk_d $end
$var reg 8 ? r_sclk_count [7:0] $end
$var wire 1 @ w_sclk_posedge $end
$var wire 1 A w_sclk_negedge $end
$var reg 1 B r_ready_d $end
$var wire 1 C w_ready_posedge $end
$var reg 3 D r_state [2:0] $end
$var reg 3 E r_next_state [2:0] $end
$var reg 8 F r_mosi_buf [7:0] $end
$var reg 7 G r_miso_buf [6:0] $end
$var reg 3 H r_bitcount [2:0] $end
$var parameter 3 I IDLE [2:0] $end
$var parameter 3 J START [2:0] $end
$var parameter 3 K INST_OUT [2:0] $end
$var parameter 3 L ADDR_OUT [2:0] $end
$var parameter 3 M WRITE_DATA [2:0] $end
$var parameter 3 N READ_DATA [2:0] $end
$var parameter 3 O ENDING [2:0] $end
$upscope $end
$upscope $end
$enddefinitions $end
#0
$dumpvars
0!
1"
x#
x$
x%
0&
0'
b0 (
0)
b0 *
b0 +
bx ,
x-
b0 .
b0 /
00
11
x2
x3
x4
05
06
b0 7
08
b0 9
b0 :
bx ;
x<
x=
x>
bx ?
x@
xA
xB
0C
bx D
bx E
bx F
bx G
bx H
b0 I
b1 J
b10 K
b11 L
b100 M
b101 N
b110 O
$end
#5000
1!
0$
10
03
b0 ?
0@
0B
b0 D
#10000
0!
00
#15000
1!
1#
0%
b0 ,
0-
10
12
04
b0 ;
0<
0=
0>
0A
b1 E
b0 F
b0 H
#20000
0!
00
#25000
1!
10
#30000
0!
00
#35000
1!
10
#40000
0!
00
#45000
1!
10
#50000
0!
00
#55000
1!
10
#60000
0!
00
#65000
1!
10
#70000
0!
00
#75000
1!
10
#80000
0!
00
#85000
1!
10
#90000
0!
00
#95000
1!
0"
10
01
b1 D
#100000
0!
00
#105000
1!
b1010 (
0)
b101101 *
b10 +
10
b1010 7
b101101 9
b10 :
#110000
0!
00
#115000
1!
1'
10
16
1C
#120000
0!
00
#125000
1!
0#
0'
b0 /
10
02
06
1=
1B
0C
b10 E
b10100 F
#130000
0!
00
#135000
1!
10
b1 ?
0B
b10 D
#140000
0!
00
#145000
1!
10
b10 ?
#150000
0!
00
#155000
1!
10
b11 ?
#160000
0!
00
#165000
1!
10
b100 ?
#170000
0!
00
#175000
1!
10
b101 ?
#180000
0!
00
#185000
1!
10
b110 ?
#190000
0!
00
#195000
1!
10
b111 ?
#200000
0!
00
#205000
1!
10
b1000 ?
#210000
0!
00
#215000
1!
10
b1001 ?
#220000
0!
00
#225000
1!
10
b1010 ?
#230000
0!
00
#235000
1!
1$
b1 /
10
13
b0 ?
1@
#240000
0!
00
#245000
1!
10
1>
b1 ?
0@
#250000
0!
00
#255000
1!
10
b10 ?
#260000
0!
00
#265000
1!
10
b11 ?
#270000
0!
00
#275000
1!
10
b100 ?
#280000
0!
00
#285000
1!
10
b101 ?
#290000
0!
00
#295000
1!
10
b110 ?
#300000
0!
00
#305000
1!
10
b111 ?
#310000
0!
00
#315000
1!
10
b1000 ?
#320000
0!
00
#325000
1!
10
b1001 ?
#330000
0!
00
#335000
1!
10
b1010 ?
#340000
0!
00
#345000
1!
0$
10
03
b0 ?
1A
#350000
0!
00
#355000
1!
10
0>
b1 ?
0A
b101000 F
b1 H
#360000
0!
00
#365000
1!
10
b10 ?
#370000
0!
00
#375000
1!
10
b11 ?
#380000
0!
00
#385000
1!
10
b100 ?
#390000
0!
00
#395000
1!
10
b101 ?
#400000
0!
00
#405000
1!
10
b110 ?
#410000
0!
00
#415000
1!
10
b111 ?
#420000
0!
00
#425000
1!
10
b1000 ?
#430000
0!
00
#435000
1!
10
b1001 ?
#440000
0!
00
#445000
1!
10
b1010 ?
#450000
0!
00
#455000
1!
1$
b10 /
10
13
b0 ?
1@
#460000
0!
00
#465000
1!
10
1>
b1 ?
0@
#470000
0!
00
#475000
1!
10
b10 ?
#480000
0!
00
#485000
1!
10
b11 ?
#490000
0!
00
#495000
1!
10
b100 ?
#500000
0!
00
#505000
1!
10
b101 ?
#510000
0!
00
#515000
1!
10
b110 ?
#520000
0!
00
#525000
1!
10
b111 ?
#530000
0!
00
#535000
1!
10
b1000 ?
#540000
0!
00
#545000
1!
10
b1001 ?
#550000
0!
00
#555000
1!
10
b1010 ?
#560000
0!
00
#565000
1!
0$
10
03
b0 ?
1A
#570000
0!
00
#575000
1!
10
0>
b1 ?
0A
b1010000 F
b10 H
#580000
0!
00
#585000
1!
10
b10 ?
#590000
0!
00
#595000
1!
10
b11 ?
#600000
0!
00
#605000
1!
10
b100 ?
#610000
0!
00
#615000
1!
10
b101 ?
#620000
0!
00
#625000
1!
10
b110 ?
#630000
0!
00
#635000
1!
10
b111 ?
#640000
0!
00
#645000
1!
10
b1000 ?
#650000
0!
00
#655000
1!
10
b1001 ?
#660000
0!
00
#665000
1!
10
b1010 ?
#670000
0!
00
#675000
1!
1$
b11 /
10
13
b0 ?
1@
#680000
0!
00
#685000
1!
10
1>
b1 ?
0@
#690000
0!
00
#695000
1!
10
b10 ?
#700000
0!
00
#705000
1!
10
b11 ?
#710000
0!
00
#715000
1!
10
b100 ?
#720000
0!
00
#725000
1!
10
b101 ?
#730000
0!
00
#735000
1!
10
b110 ?
#740000
0!
00
#745000
1!
10
b111 ?
#750000
0!
00
#755000
1!
10
b1000 ?
#760000
0!
00
#765000
1!
10
b1001 ?
#770000
0!
00
#775000
1!
10
b1010 ?
#780000
0!
00
#785000
1!
0$
10
03
b0 ?
1A
#790000
0!
00
#795000
1!
10
0>
b1 ?
0A
b10100000 F
b11 H
#800000
0!
00
#805000
1!
10
b10 ?
#810000
0!
00
#815000
1!
10
b11 ?
#820000
0!
00
#825000
1!
10
b100 ?
#830000
0!
00
#835000
1!
10
b101 ?
#840000
0!
00
#845000
1!
10
b110 ?
#850000
0!
00
#855000
1!
10
b111 ?
#860000
0!
00
#865000
1!
10
b1000 ?
#870000
0!
00
#875000
1!
10
b1001 ?
#880000
0!
00
#885000
1!
10
b1010 ?
#890000
0!
00
#895000
1!
1$
b100 /
10
13
b0 ?
1@
#900000
0!
00
#905000
1!
10
1>
b1 ?
0@
#910000
0!
00
#915000
1!
10
b10 ?
#920000
0!
00
#925000
1!
10
b11 ?
#930000
0!
00
#935000
1!
10
b100 ?
#940000
0!
00
#945000
1!
10
b101 ?
#950000
0!
00
#955000
1!
10
b110 ?
#960000
0!
00
#965000
1!
10
b111 ?
#970000
0!
00
#975000
1!
10
b1000 ?
#980000
0!
00
#985000
1!
10
b1001 ?
#990000
0!
00
#995000
1!
10
b1010 ?
#1000000
0!
00
#1005000
1!
0$
10
03
b0 ?
1A
#1010000
0!
00
#1015000
1!
1%
10
14
0>
b1 ?
0A
b1000000 F
b100 H
#1020000
0!
00
#1025000
1!
10
b10 ?
#1030000
0!
00
#1035000
1!
10
b11 ?
#1040000
0!
00
#1045000
1!
10
b100 ?
#1050000
0!
00
#1055000
1!
10
b101 ?
#1060000
0!
00
#1065000
1!
10
b110 ?
#1070000
0!
00
#1075000
1!
10
b111 ?
#1080000
0!
00
#1085000
1!
10
b1000 ?
#1090000
0!
00
#1095000
1!
10
b1001 ?
#1100000
0!
00
#1105000
1!
10
b1010 ?
#1110000
0!
00
#1115000
1!
1$
b1 .
b101 /
10
13
b0 ?
1@
#1120000
0!
00
#1125000
1!
10
1>
b1 ?
0@
#1130000
0!
00
#1135000
1!
10
b10 ?
#1140000
0!
00
#1145000
1!
10
b11 ?
#1150000
0!
00
#1155000
1!
10
b100 ?
#1160000
0!
00
#1165000
1!
10
b101 ?
#1170000
0!
00
#1175000
1!
10
b110 ?
#1180000
0!
00
#1185000
1!
10
b111 ?
#1190000
0!
00
#1195000
1!
10
b1000 ?
#1200000
0!
00
#1205000
1!
10
b1001 ?
#1210000
0!
00
#1215000
1!
10
b1010 ?
#1220000
0!
00
#1225000
1!
0$
10
03
b0 ?
1A
#1230000
0!
00
#1235000
1!
0%
10
04
0>
b1 ?
0A
b10000000 F
b101 H
#1240000
0!
00
#1245000
1!
10
b10 ?
#1250000
0!
00
#1255000
1!
10
b11 ?
#1260000
0!
00
#1265000
1!
10
b100 ?
#1270000
0!
00
#1275000
1!
10
b101 ?
#1280000
0!
00
#1285000
1!
10
b110 ?
#1290000
0!
00
#1295000
1!
10
b111 ?
#1300000
0!
00
#1305000
1!
10
b1000 ?
#1310000
0!
00
#1315000
1!
10
b1001 ?
#1320000
0!
00
#1325000
1!
10
b1010 ?
#1330000
0!
00
#1335000
1!
1$
b10 .
b110 /
10
13
b0 ?
1@
#1340000
0!
00
#1345000
1!
10
1>
b1 ?
0@
#1350000
0!
00
#1355000
1!
10
b10 ?
#1360000
0!
00
#1365000
1!
10
b11 ?
#1370000
0!
00
#1375000
1!
10
b100 ?
#1380000
0!
00
#1385000
1!
10
b101 ?
#1390000
0!
00
#1395000
1!
10
b110 ?
#1400000
0!
00
#1405000
1!
10
b111 ?
#1410000
0!
00
#1415000
1!
10
b1000 ?
#1420000
0!
00
#1425000
1!
10
b1001 ?
#1430000
0!
00
#1435000
1!
10
b1010 ?
#1440000
0!
00
#1445000
1!
0$
10
03
b0 ?
1A
#1450000
0!
00
#1455000
1!
1%
10
14
0>
b1 ?
0A
b0 F
b110 H
#1460000
0!
00
#1465000
1!
10
b10 ?
#1470000
0!
00
#1475000
1!
10
b11 ?
#1480000
0!
00
#1485000
1!
10
b100 ?
#1490000
0!
00
#1495000
1!
10
b101 ?
#1500000
0!
00
#1505000
1!
10
b110 ?
#1510000
0!
00
#1515000
1!
10
b111 ?
#1520000
0!
00
#1525000
1!
10
b1000 ?
#1530000
0!
00
#1535000
1!
10
b1001 ?
#1540000
0!
00
#1545000
1!
10
b1010 ?
#1550000
0!
00
#1555000
1!
1$
b101 .
b111 /
10
13
b0 ?
1@
#1560000
0!
00
#1565000
1!
10
1>
b1 ?
0@
#1570000
0!
00
#1575000
1!
10
b10 ?
#1580000
0!
00
#1585000
1!
10
b11 ?
#1590000
0!
00
#1595000
1!
10
b100 ?
#1600000
0!
00
#1605000
1!
10
b101 ?
#1610000
0!
00
#1615000
1!
10
b110 ?
#1620000
0!
00
#1625000
1!
10
b111 ?
#1630000
0!
00
#1635000
1!
10
b1000 ?
#1640000
0!
00
#1645000
1!
10
b1001 ?
#1650000
0!
00
#1655000
1!
10
b1010 ?
#1660000
0!
00
#1665000
1!
0$
10
03
b0 ?
1A
#1670000
0!
00
#1675000
1!
0%
10
04
0>
b1 ?
0A
b111 H
#1680000
0!
00
#1685000
1!
10
b10 ?
#1690000
0!
00
#1695000
1!
10
b11 ?
#1700000
0!
00
#1705000
1!
10
b100 ?
#1710000
0!
00
#1715000
1!
10
b101 ?
#1720000
0!
00
#1725000
1!
10
b110 ?
#1730000
0!
00
#1735000
1!
10
b111 ?
#1740000
0!
00
#1745000
1!
10
b1000 ?
#1750000
0!
00
#1755000
1!
10
b1001 ?
#1760000
0!
00
#1765000
1!
10
b1010 ?
#1770000
0!
00
#1775000
1!
1$
b1010 .
b1000 /
10
13
b0 ?
1@
#1780000
0!
00
#1785000
1!
10
1>
b1 ?
0@
#1790000
0!
00
#1795000
1!
10
b10 ?
#1800000
0!
00
#1805000
1!
10
b11 ?
#1810000
0!
00
#1815000
1!
10
b100 ?
#1820000
0!
00
#1825000
1!
10
b101 ?
#1830000
0!
00
#1835000
1!
10
b110 ?
#1840000
0!
00
#1845000
1!
10
b111 ?
#1850000
0!
00
#1855000
1!
10
b1000 ?
#1860000
0!
00
#1865000
1!
10
b1001 ?
#1870000
0!
00
#1875000
1!
10
b1010 ?
#1880000
0!
00
#1885000
1!
0$
10
03
b0 ?
1A
#1890000
0!
00
#1895000
1!
10
0>
b1 ?
0A
b11 E
b1011010 F
b0 H
#1900000
0!
00
#1905000
1!
10
b10 ?
b11 D
#1910000
0!
00
#1915000
1!
10
b11 ?
#1920000
0!
00
#1925000
1!
10
b100 ?
#1930000
0!
00
#1935000
1!
10
b101 ?
#1940000
0!
00
#1945000
1!
10
b110 ?
#1950000
0!
00
#1955000
1!
10
b111 ?
#1960000
0!
00
#1965000
1!
10
b1000 ?
#1970000
0!
00
#1975000
1!
10
b1001 ?
#1980000
0!
00
#1985000
1!
10
b1010 ?
#1990000
0!
00
#1995000
1!
1$
b10100 .
b1001 /
10
13
b0 ?
1@
#2000000
0!
00
#2005000
1!
10
1>
b1 ?
0@
#2010000
0!
00
#2015000
1!
10
b10 ?
#2020000
0!
00
#2025000
1!
10
b11 ?
#2030000
0!
00
#2035000
1!
10
b100 ?
#2040000
0!
00
#2045000
1!
10
b101 ?
#2050000
0!
00
#2055000
1!
10
b110 ?
#2060000
0!
00
#2065000
1!
10
b111 ?
#2070000
0!
00
#2075000
1!
10
b1000 ?
#2080000
0!
00
#2085000
1!
10
b1001 ?
#2090000
0!
00
#2095000
1!
10
b1010 ?
#2100000
0!
00
#2105000
1!
0$
10
03
b0 ?
1A
#2110000
0!
00
#2115000
1!
10
0>
b1 ?
0A
b10110100 F
b1 H
#2120000
0!
00
#2125000
1!
10
b10 ?
#2130000
0!
00
#2135000
1!
10
b11 ?
#2140000
0!
00
#2145000
1!
10
b100 ?
#2150000
0!
00
#2155000
1!
10
b101 ?
#2160000
0!
00
#2165000
1!
10
b110 ?
#2170000
0!
00
#2175000
1!
10
b111 ?
#2180000
0!
00
#2185000
1!
10
b1000 ?
#2190000
0!
00
#2195000
1!
10
b1001 ?
#2200000
0!
00
#2205000
1!
10
b1010 ?
#2210000
0!
00
#2215000
1!
1$
b101000 .
b1010 /
10
13
b0 ?
1@
#2220000
0!
00
#2225000
1!
10
1>
b1 ?
0@
#2230000
0!
00
#2235000
1!
10
b10 ?
#2240000
0!
00
#2245000
1!
10
b11 ?
#2250000
0!
00
#2255000
1!
10
b100 ?
#2260000
0!
00
#2265000
1!
10
b101 ?
#2270000
0!
00
#2275000
1!
10
b110 ?
#2280000
0!
00
#2285000
1!
10
b111 ?
#2290000
0!
00
#2295000
1!
10
b1000 ?
#2300000
0!
00
#2305000
1!
10
b1001 ?
#2310000
0!
00
#2315000
1!
10
b1010 ?
#2320000
0!
00
#2325000
1!
0$
10
03
b0 ?
1A
#2330000
0!
00
#2335000
1!
1%
10
14
0>
b1 ?
0A
b1101000 F
b10 H
#2340000
0!
00
#2345000
1!
10
b10 ?
#2350000
0!
00
#2355000
1!
10
b11 ?
#2360000
0!
00
#2365000
1!
10
b100 ?
#2370000
0!
00
#2375000
1!
10
b101 ?
#2380000
0!
00
#2385000
1!
10
b110 ?
#2390000
0!
00
#2395000
1!
10
b111 ?
#2400000
0!
00
#2405000
1!
10
b1000 ?
#2410000
0!
00
#2415000
1!
10
b1001 ?
#2420000
0!
00
#2425000
1!
10
b1010 ?
#2430000
0!
00
#2435000
1!
1$
b1010001 .
b1011 /
10
13
b0 ?
1@
#2440000
0!
00
#2445000
1!
10
1>
b1 ?
0@
#2450000
0!
00
#2455000
1!
10
b10 ?
#2460000
0!
00
#2465000
1!
10
b11 ?
#2470000
0!
00
#2475000
1!
10
b100 ?
#2480000
0!
00
#2485000
1!
10
b101 ?
#2490000
0!
00
#2495000
1!
10
b110 ?
#2500000
0!
00
#2505000
1!
10
b111 ?
#2510000
0!
00
#2515000
1!
10
b1000 ?
#2520000
0!
00
#2525000
1!
10
b1001 ?
#2530000
0!
00
#2535000
1!
10
b1010 ?
#2540000
0!
00
#2545000
1!
0$
10
03
b0 ?
1A
#2550000
0!
00
#2555000
1!
0%
10
04
0>
b1 ?
0A
b11010000 F
b11 H
#2560000
0!
00
#2565000
1!
10
b10 ?
#2570000
0!
00
#2575000
1!
10
b11 ?
#2580000
0!
00
#2585000
1!
10
b100 ?
#2590000
0!
00
#2595000
1!
10
b101 ?
#2600000
0!
00
#2605000
1!
10
b110 ?
#2610000
0!
00
#2615000
1!
10
b111 ?
#2620000
0!
00
#2625000
1!
10
b1000 ?
#2630000
0!
00
#2635000
1!
10
b1001 ?
#2640000
0!
00
#2645000
1!
10
b1010 ?
#2650000
0!
00
#2655000
1!
1$
b10100010 .
b1100 /
10
13
b0 ?
1@
#2660000
0!
00
#2665000
1!
10
1>
b1 ?
0@
#2670000
0!
00
#2675000
1!
10
b10 ?
#2680000
0!
00
#2685000
1!
10
b11 ?
#2690000
0!
00
#2695000
1!
10
b100 ?
#2700000
0!
00
#2705000
1!
10
b101 ?
#2710000
0!
00
#2715000
1!
10
b110 ?
#2720000
0!
00
#2725000
1!
10
b111 ?
#2730000
0!
00
#2735000
1!
10
b1000 ?
#2740000
0!
00
#2745000
1!
10
b1001 ?
#2750000
0!
00
#2755000
1!
10
b1010 ?
#2760000
0!
00
#2765000
1!
0$
10
03
b0 ?
1A
#2770000
0!
00
#2775000
1!
1%
10
14
0>
b1 ?
0A
b10100000 F
b100 H
#2780000
0!
00
#2785000
1!
10
b10 ?
#2790000
0!
00
#2795000
1!
10
b11 ?
#2800000
0!
00
#2805000
1!
10
b100 ?
#2810000
0!
00
#2815000
1!
10
b101 ?
#2820000
0!
00
#2825000
1!
10
b110 ?
#2830000
0!
00
#2835000
1!
10
b111 ?
#2840000
0!
00
#2845000
1!
10
b1000 ?
#2850000
0!
00
#2855000
1!
10
b1001 ?
#2860000
0!
00
#2865000
1!
10
b1010 ?
#2870000
0!
00
#2875000
1!
1$
b101000101 .
b1101 /
10
13
b0 ?
1@
#2880000
0!
00
#2885000
1!
10
1>
b1 ?
0@
#2890000
0!
00
#2895000
1!
10
b10 ?
#2900000
0!
00
#2905000
1!
10
b11 ?
#2910000
0!
00
#2915000
1!
10
b100 ?
#2920000
0!
00
#2925000
1!
10
b101 ?
#2930000
0!
00
#2935000
1!
10
b110 ?
#2940000
0!
00
#2945000
1!
10
b111 ?
#2950000
0!
00
#2955000
1!
10
b1000 ?
#2960000
0!
00
#2965000
1!
10
b1001 ?
#2970000
0!
00
#2975000
1!
10
b1010 ?
#2980000
0!
00
#2985000
1!
0$
10
03
b0 ?
1A
#2990000
0!
00
#2995000
1!
10
0>
b1 ?
0A
b1000000 F
b101 H
#3000000
0!
00
#3005000
1!
10
b10 ?
#3010000
0!
00
#3015000
1!
10
b11 ?
#3020000
0!
00
#3025000
1!
10
b100 ?
#3030000
0!
00
#3035000
1!
10
b101 ?
#3040000
0!
00
#3045000
1!
10
b110 ?
#3050000
0!
00
#3055000
1!
10
b111 ?
#3060000
0!
00
#3065000
1!
10
b1000 ?
#3070000
0!
00
#3075000
1!
10
b1001 ?
#3080000
0!
00
#3085000
1!
10
b1010 ?
#3090000
0!
00
#3095000
1!
1$
b1010001011 .
b1110 /
10
13
b0 ?
1@
#3100000
0!
00
#3105000
1!
10
1>
b1 ?
0@
#3110000
0!
00
#3115000
1!
10
b10 ?
#3120000
0!
00
#3125000
1!
10
b11 ?
#3130000
0!
00
#3135000
1!
10
b100 ?
#3140000
0!
00
#3145000
1!
10
b101 ?
#3150000
0!
00
#3155000
1!
10
b110 ?
#3160000
0!
00
#3165000
1!
10
b111 ?
#3170000
0!
00
#3175000
1!
10
b1000 ?
#3180000
0!
00
#3185000
1!
10
b1001 ?
#3190000
0!
00
#3195000
1!
10
b1010 ?
#3200000
0!
00
#3205000
1!
0$
10
03
b0 ?
1A
#3210000
0!
00
#3215000
1!
0%
10
04
0>
b1 ?
0A
b10000000 F
b110 H
#3220000
0!
00
#3225000
1!
10
b10 ?
#3230000
0!
00
#3235000
1!
10
b11 ?
#3240000
0!
00
#3245000
1!
10
b100 ?
#3250000
0!
00
#3255000
1!
10
b101 ?
#3260000
0!
00
#3265000
1!
10
b110 ?
#3270000
0!
00
#3275000
1!
10
b111 ?
#3280000
0!
00
#3285000
1!
10
b1000 ?
#3290000
0!
00
#3295000
1!
10
b1001 ?
#3300000
0!
00
#3305000
1!
10
b1010 ?
#3310000
0!
00
#3315000
1!
1$
b10100010110 .
b1111 /
10
13
b0 ?
1@
#3320000
0!
00
#3325000
1!
10
1>
b1 ?
0@
#3330000
0!
00
#3335000
1!
10
b10 ?
#3340000
0!
00
